[
  {
    "anonymous": false,
    "inputs": [
      {
        "indexed": false,
        "internalType": "uint8",
        "name": "version",
        "type": "uint8"
      }
    ],
    "name": "Initialized",
    "type": "event"
  },
  {
    "anonymous": false,
    "inputs": [
      {
        "indexed": true,
        "internalType": "uint256",
        "name": "id",
        "type": "uint256"
      },
      {
        "indexed": false,
        "internalType": "uint256",
        "name": "points",
        "type": "uint256"
      },
      {
        "indexed": false,
        "internalType": "uint256",
        "name": "timeExtension",
        "type": "uint256"
      },
      {
        "indexed": false,
        "internalType": "string",
        "name": "gameName",
        "type": "string"
      }
    ],
    "name": "Played",
    "type": "event"
  },
  {
    "anonymous": false,
    "inputs": [
      {
        "indexed": true,
        "internalType": "uint256",
        "name": "id",
        "type": "uint256"
      },
      {
        "indexed": false,
        "internalType": "int256",
        "name": "points",
        "type": "int256"
      },
      {
        "indexed": false,
        "internalType": "int256",
        "name": "timeExtension",
        "type": "int256"
      },
      {
        "indexed": false,
        "internalType": "string",
        "name": "gameName",
        "type": "string"
      }
    ],
    "name": "PlayedV2",
    "type": "event"
  },
  {
    "inputs": [
      {
        "internalType": "uint256",
        "name": "nftID",
        "type": "uint256"
      }
    ],
    "name": "boxGameGetCoolDownTimePerNFT",
    "outputs": [
      {
        "internalType": "uint256",
        "name": "",
        "type": "uint256"
      }
    ],
    "stateMutability": "view",
    "type": "function"
  },
  {
    "inputs": [
      {
        "internalType": "uint256",
        "name": "nftID",
        "type": "uint256"
      }
    ],
    "name": "boxGameGetCoolDownTimeWithStar",
    "outputs": [
      {
        "internalType": "uint256",
        "name": "",
        "type": "uint256"
      }
    ],
    "stateMutability": "view",
    "type": "function"
  },
  {
    "inputs": [],
    "name": "boxGameInitialize",
    "outputs": [],
    "stateMutability": "nonpayable",
    "type": "function"
  },
  {
    "inputs": [],
    "name": "boxGameInitialize2",
    "outputs": [],
    "stateMutability": "nonpayable",
    "type": "function"
  },
  {
    "inputs": [
      {
        "internalType": "uint256",
        "name": "nftID",
        "type": "uint256"
      },
      {
        "internalType": "uint256",
        "name": "seed",
        "type": "uint256"
      }
    ],
    "name": "boxGamePlay",
    "outputs": [
      {
        "internalType": "uint256",
        "name": "points",
        "type": "uint256"
      },
      {
        "internalType": "uint256",
        "name": "timeExtension",
        "type": "uint256"
      }
    ],
    "stateMutability": "nonpayable",
    "type": "function"
  },
  {
    "inputs": [
      {
        "internalType": "uint256",
        "name": "nftID",
        "type": "uint256"
      },
      {
        "internalType": "uint256",
        "name": "seed",
        "type": "uint256"
      }
    ],
    "name": "boxGamePlayWithStar",
    "outputs": [
      {
        "internalType": "uint256",
        "name": "points",
        "type": "uint256"
      },
      {
        "internalType": "uint256",
        "name": "timeExtension",
        "type": "uint256"
      }
    ],
    "stateMutability": "nonpayable",
    "type": "function"
  },
  {
    "inputs": [
      {
        "internalType": "uint256",
        "name": "_coolDownTime",
        "type": "uint256"
      }
    ],
    "name": "boxGameSetGlobalCoolDownTime",
    "outputs": [],
    "stateMutability": "nonpayable",
    "type": "function"
  },
  {
    "inputs": [
      {
        "internalType": "uint256[5]",
        "name": "_pointRewards",
        "type": "uint256[5]"
      }
    ],
    "name": "boxGameSetPointRewards",
    "outputs": [],
    "stateMutability": "nonpayable",
    "type": "function"
  },
  {
    "inputs": [
      {
        "internalType": "uint256[5]",
        "name": "_timeRewards",
        "type": "uint256[5]"
      }
    ],
    "name": "boxGameSetTimeRewards",
    "outputs": [],
    "stateMutability": "nonpayable",
    "type": "function"
  }
]